{
  "tasks": [
    {
      "name": "supersix-live-scoreextractor",
      "month": "*",
      "day": "*",
      "weekday": "6",
      "hour": "15-17",
      "minute": "*/10",
      "command": "~/lib/python ~/build/agents/supersix/score-extractor.py -l PL ELC EL1 EL2 -s 0"
    },
    {
      "name": "supersix-final-scoreextractor-pl",
      "month": "*",
      "day": "*",
      "weekday": "*",
      "hour": "22",
      "minute": "0",
      "command": "~/lib/python ~/build/agents/supersix/final-score-extractor.py -l PL"
    },
    {
      "name": "supersix-final-scoreextractor-elc",
      "month": "*",
      "day": "*",
      "weekday": "*",
      "hour": "22",
      "minute": "1",
      "command": "~/lib/python ~/build/agents/supersix/final-score-extractor.py -l ELC"
    },
    {
      "name": "supersix-final-scoreextractor-el1",
      "month": "*",
      "day": "*",
      "weekday": "*",
      "hour": "22",
      "minute": "2",
      "command": "~/lib/python ~/build/agents/supersix/final-score-extractor.py -l EL1"
    },
    {
      "name": "supersix-final-scoreextractor-el2",
      "month": "*",
      "day": "*",
      "weekday": "*",
      "hour": "22",
      "minute": "3",
      "command": "~/lib/python ~/build/agents/supersix/final-score-extractor.py -l EL2"
    },
    {
      "name": "supersix-matchextractor-pl",
      "month": "*",
      "day": "*",
      "weekday": "*",
      "hour": "19",
      "minute": "5",
      "command": "~/lib/python ~/build/agents/supersix/match-extractor.py -l PL -ma 3"
    },
    {
      "name": "supersix-matchextractor-elc",
      "month": "*",
      "day": "*",
      "weekday": "*",
      "hour": "19",
      "minute": "15",
      "command": "~/lib/python ~/build/agents/supersix/match-extractor.py -l ELC -ma 3"
    },
    {
      "name": "supersix-matchextractor-el1",
      "month": "*",
      "day": "*",
      "weekday": "*",
      "hour": "19",
      "minute": "25",
      "command": "~/lib/python ~/build/agents/supersix/match-extractor.py -l EL1 -ma 3"
    },
    {
      "name": "supersix-matchextractor-el2",
      "month": "*",
      "day": "*",
      "weekday": "*",
      "hour": "19",
      "minute": "35",
      "command": "~/lib/python ~/build/agents/supersix/match-extractor.py -l EL2 -ma 3"
    },
    {
      "name": "supersix-leagueextractor",
      "month": "*",
      "day": "*",
      "weekday": "*",
      "hour": "23",
      "minute": "15",
      "command": "~/lib/python ~/build/agents/supersix/league-extractor.py"
    },
    {
      "name": "euros-leagueextractor",
      "month": "6,7",
      "day": "*",
      "weekday": "*",
      "hour": "3",
      "minute": "0",
      "command": "~/lib/python ~/build/agents/supersix/euros-league-extractor.py"
    },
    {
      "name": "euros-matchextractor",
      "month": "6,7",
      "day": "*",
      "weekday": "*",
      "hour": "*/3",
      "minute": "40",
      "command": "~/lib/python ~/build/agents/supersix/euros-match-extractor.py"
    },
    {
      "name": "euros-scoreextractor",
      "month": "6,7",
      "day": "*",
      "weekday": "*",
      "hour": "14,15,16,17,18,19,20,21,22,23",
      "minute": "*/5",
      "command": "~/lib/python ~/build/agents/supersix/euros-score-extractor.py -s 0"
    },
  ]
}
